mosaic_qt6/__init__.py
mosaic_qt6/mosaic.py
mosaic_qt6-1.0.1.dist-info/licenses/LICENSE
mosaic_qt6-1.0.1.dist-info/METADATA
mosaic_qt6-1.0.1.dist-info/WHEEL
mosaic_qt6-1.0.1.dist-info/top_level.txt
mosaic_qt6-1.0.1.dist-info/RECORD
