Metadata-Version: 2.4
Name: mosaic_qt6
Version: 1.0.1
Summary: Create Qt6 GUIs using HTML-like syntax!
Author-email: DCreator112 <dylanlmclark@gmail.com>
License-Expression: MIT
Project-URL: Homepage, https://dcreator112.xyz/mosaic
Classifier: Programming Language :: Python :: 3
Classifier: Operating System :: OS Independent
Requires-Python: >=3.9
License-File: LICENSE
Requires-Dist: BeautifulSoup4
Requires-Dist: PySide6
Dynamic: license-file
